youtrack_python_cli/__init__.py
youtrack_python_cli/_version.py
youtrack_python_cli/cli.py
youtrack_python_cli-0.2.0.dist-info/METADATA
youtrack_python_cli-0.2.0.dist-info/WHEEL
youtrack_python_cli-0.2.0.dist-info/entry_points.txt
youtrack_python_cli-0.2.0.dist-info/RECORD
