Metadata-Version: 2.1
Name: youtrack-python-cli
Version: 0.2.0
Summary: Basic Youtrack CLI in python
Requires-Python: >=3.7.2,<4.0.0
Classifier: Programming Language :: Python :: 3
Classifier: Programming Language :: Python :: 3.8
Classifier: Programming Language :: Python :: 3.9
Classifier: Programming Language :: Python :: 3.10
Classifier: Programming Language :: Python :: 3.11
Classifier: Programming Language :: Python :: 3.12
Requires-Dist: click (>=8.1.3,<9.0.0)
Requires-Dist: importlib-metadata (>=6.0.0,<7.0.0)
Requires-Dist: rich (>=13.3.2,<14.0.0)
Requires-Dist: youtrack-python-openapi (>=2023.1,<2024.0)
